dsegmenter/__init__.py
dsegmenter/common.py
dsegmenter/bparseg/__init__.py
dsegmenter/bparseg/align.py
dsegmenter/bparseg/bparsegmenter.py
dsegmenter/bparseg/constants.py
dsegmenter/bparseg/constituency_tree.py
dsegmenter/bparseg/data/bpar.model
dsegmenter/bparseg/data/bpar.model_01.npy
dsegmenter/bparseg/data/bpar.model_02.npy
dsegmenter/bparseg/data/bpar.model_03.npy
dsegmenter/bparseg/data/bpar.model_04.npy
dsegmenter/bparseg/data/bpar.model_05.npy
dsegmenter/bparseg/data/bpar.model_06.npy
dsegmenter/edseg/__init__.py
dsegmenter/edseg/chunking.py
dsegmenter/edseg/clause_segmentation.py
dsegmenter/edseg/conll.py
dsegmenter/edseg/data.py
dsegmenter/edseg/edssegmenter.py
dsegmenter/edseg/finitestateparsing.py
dsegmenter/edseg/util.py
dsegmenter/edseg/data/dass_verbs.txt
dsegmenter/edseg/data/discourse_preps.txt
dsegmenter/edseg/data/finite_verbs.txt
dsegmenter/edseg/data/reporting_verbs.txt
dsegmenter/edseg/data/skip_rules.txt
dsegmenter/evaluation/__init__.py
dsegmenter/evaluation/align.py
dsegmenter/evaluation/metrics.py
dsegmenter/evaluation/parseval.py
dsegmenter/evaluation/segmentation.py
dsegmenter/evaluation/alpha/UnitizingAnnotationEvaluator.class
dsegmenter/evaluation/alpha/UnitizingAnnotationEvaluator.java
dsegmenter/evaluation/alpha/dkpro-statistics-agreement-2.1.0.LICENSE.txt
dsegmenter/evaluation/alpha/dkpro-statistics-agreement-2.1.0.jar
dsegmenter/evaluation/alpha/eval_alpha_unit.sh
dsegmenter/mateseg/__init__.py
dsegmenter/mateseg/dependency_graph.py
dsegmenter/mateseg/matesegmenter.py
dsegmenter/mateseg/segmentation_tree.py
dsegmenter/mateseg/data/mate.model
dsegmenter/treeseg/__init__.py
dsegmenter/treeseg/constants.py
dsegmenter/treeseg/discourse_segment.py
dsegmenter/treeseg/treesegmenter.py
dsegmenter-0.2.12.data/scripts/discourse_segmenter
dsegmenter-0.2.12.data/scripts/evaluation
dsegmenter-0.2.12.dist-info/DESCRIPTION.rst
dsegmenter-0.2.12.dist-info/METADATA
dsegmenter-0.2.12.dist-info/RECORD
dsegmenter-0.2.12.dist-info/WHEEL
dsegmenter-0.2.12.dist-info/metadata.json
dsegmenter-0.2.12.dist-info/top_level.txt
