Metadata-Version: 2.0
Name: dsegmenter
Version: 0.2.12
Summary: Collection of discourse segmenters (with pre-trained models for German)
Home-page: https://github.com/discourse-lab/DiscourseSegmenter
Author: Wladimir Sidorenko (Uladzimir Sidarenka)
Author-email: sidarenk@uni-potsdam.de
License: MIT
Keywords: discourse segmentation NLP linguistics
Platform: UNKNOWN
Classifier: Development Status :: 4 - Beta
Classifier: Environment :: Console
Classifier: Intended Audience :: Science/Research
Classifier: License :: OSI Approved :: MIT License
Classifier: Natural Language :: German
Classifier: Operating System :: Unix
Classifier: Operating System :: MacOS
Classifier: Programming Language :: Python :: 2
Classifier: Programming Language :: Python :: 2.6
Classifier: Programming Language :: Python :: 2.7
Classifier: Topic :: Text Processing :: Linguistic
Provides: dsegmenter (0.2.1)
Requires-Dist: pip (>=8.1.0)
Requires-Dist: segeval (>=2.0)
Requires-Dist: nltk (>=3.0.2)
Requires-Dist: scikit-learn (>=0.18.1)
Requires-Dist: numpy (>=1.9.2)
Requires-Dist: scipy (>=0.9)
